Tool.py
sztestlib/__init__.py
sztestlib/szlibone.py
sztestlib666-1.0.0.dist-info/LICENSE.txt
sztestlib666-1.0.0.dist-info/METADATA
sztestlib666-1.0.0.dist-info/WHEEL
sztestlib666-1.0.0.dist-info/top_level.txt
sztestlib666-1.0.0.dist-info/RECORD
