Metadata-Version: 2.1
Name: sztestlib666
Version: 1.0.0
Summary: this is a niu bi lib
Home-page: https://XXX.com
Author: Sz
Author-email: 1334887352@qq.com
License: UNKNOWN
Platform: UNKNOWN
